kdenlive_mcp/__init__.py
kdenlive_mcp/py.typed
kdenlive_mcp/server.py
kdenlive_mcp/tools/__init__.py
kdenlive_mcp/tools/_common.py
kdenlive_mcp/tools/asset.py
kdenlive_mcp/tools/bin.py
kdenlive_mcp/tools/composition.py
kdenlive_mcp/tools/effects.py
kdenlive_mcp/tools/flows.py
kdenlive_mcp/tools/project.py
kdenlive_mcp/tools/render.py
kdenlive_mcp/tools/timeline.py
kdenlive_mcp/tools/transition.py
kdenlive_mcp/tools/utility.py
kdenlive_mcp-0.2.1.dist-info/METADATA
kdenlive_mcp-0.2.1.dist-info/WHEEL
kdenlive_mcp-0.2.1.dist-info/entry_points.txt
kdenlive_mcp-0.2.1.dist-info/licenses/LICENSE
kdenlive_mcp-0.2.1.dist-info/RECORD
