Metadata-Version: 2.4
Name: kdenlive-mcp
Version: 0.2.1
Summary: MCP server for Kdenlive video editor automation
Project-URL: Homepage, https://github.com/IO-AtelierTech/kdenlive-automation
Project-URL: Repository, https://github.com/IO-AtelierTech/kdenlive-automation
Project-URL: Documentation, https://github.com/IO-AtelierTech/kdenlive-automation#readme
Project-URL: Issues, https://github.com/IO-AtelierTech/kdenlive-automation/issues
Project-URL: Changelog, https://github.com/IO-AtelierTech/kdenlive-automation/blob/main/CHANGELOG.md
Author-email: IO-AtelierTech <ioateliertech@gmail.com>
License: MIT
License-File: LICENSE
Keywords: ai,automation,claude,editing,kdenlive,mcp,model-context-protocol,video
Classifier: Development Status :: 3 - Alpha
Classifier: Framework :: AsyncIO
Classifier: Intended Audience :: Developers
Classifier: License :: OSI Approved :: MIT License
Classifier: Operating System :: OS Independent
Classifier: Programming Language :: Python :: 3
Classifier: Programming Language :: Python :: 3.11
Classifier: Programming Language :: Python :: 3.12
Classifier: Programming Language :: Python :: 3.13
Classifier: Topic :: Multimedia :: Video
Classifier: Topic :: Scientific/Engineering :: Artificial Intelligence
Classifier: Typing :: Typed
Requires-Python: >=3.11
Requires-Dist: kdenlive-api>=0.2.1
Requires-Dist: mcp>=1.0
Provides-Extra: dev
Requires-Dist: pytest-asyncio>=0.23; extra == 'dev'
Requires-Dist: pytest>=8.0; extra == 'dev'
